Metadata-Version: 2.1
Name: vk-face-recognition
Version: 1.1.4
Summary: Creating a database with biometrics of persons and subsequent search on it
Home-page: https://github.com/b0shka/vk_face_recognition
Author: b0shka
Author-email: user.b0shka@gmail.com
License: MIT license
Platform: UNKNOWN
Classifier: Programming Language :: Python :: 3.8
Classifier: License :: OSI Approved :: MIT License
Classifier: Operating System :: OS Independent
Classifier: Intended Audience :: Developers
